Metadata-Version: 1.0
Name: calculate-bmi
Version: 0.2
Summary: Calculate Body-Mass Index
Home-page: UNKNOWN
Author: Alamgir Hossain
Author-email: UNKNOWN
License: UNKNOWN
Platform: UNKNOWN
